tolias_lab_to_nwb/__init__.py
tolias_lab_to_nwb/convert.py
tolias_lab_to_nwb/data_prep.py
tolias_lab_to_nwb/EphysExtraction/__init__.py
tolias_lab_to_nwb/EphysExtraction/ephys_extractor.py
tolias_lab_to_nwb/EphysExtraction/ephys_features.py
tolias_lab_to_nwb-0.3.0.dist-info/METADATA
tolias_lab_to_nwb-0.3.0.dist-info/WHEEL
tolias_lab_to_nwb-0.3.0.dist-info/top_level.txt
tolias_lab_to_nwb-0.3.0.dist-info/RECORD
