Metadata-Version: 2.1
Name: tolias-lab-to-nwb
Version: 0.3.0
Summary: tool to convert Tolias Lab matlab intracellular electrophysiology data into NWB:N format
Home-page: UNKNOWN
Author: Ben Dichter
Author-email: ben.dichter@gmail.com
License: UNKNOWN
Platform: UNKNOWN
Requires-Dist: pandas
Requires-Dist: numpy
Requires-Dist: scipy
Requires-Dist: ruamel.yaml
Requires-Dist: pynwb
Requires-Dist: nwbn-conversion-tools (==0.2.0)
